Workbook

Sheet Proposal Summery
B2: Proposal Summery
B3: Service Location | C3: Count of Laptop | D3: PTPQ | E3: No of Quarters | F3: Quarterly lease rent for all units payable in Advance | G3: Total leasing amount for 12 Quarters
B4: VW Group Digital Solutions Congo Pune (SEZ) - Lenovo TP T14 AMD G5 with Accessories | C4: 110 | D4: ='FMV Lease - Pune SEZ'!B10 -> 0 | E4: 12 | F4: ='FMV Lease - Pune SEZ'!B12 -> 0 | G4: =F4*E4 -> 0
B5: VW Group Digital Solutions Ganges (Non SEZ) - Lenovo TP T14 AMD G5 with Accessories | C5: 110 | D5: ='FMV Lease - Pune Non SEZ'!B10 -> 0 | E5: 12 | F5: ='FMV Lease - Pune Non SEZ'!B12 -> 0 | G5: =F5*E5 -> 0
B6: VW Group Digital Solutions Gurgaon - Lenovo TP T14 AMD G5 with Accessories | C6: 110 | D6: ='FMV Lease - GGN'!B10 -> 0 | E6: 12 | F6: ='FMV Lease - GGN'!B12 -> 0 | G6: =F6*E6 -> 0
B7: VW Group Digital Solutions Bangalore - Lenovo TP T14 AMD G5 with Accessories | C7: 110 | D7: ='FMV Lease - BLR'!B10 -> 0 | E7: 12 | F7: ='FMV Lease - BLR'!B12 -> 0 | G7: =F7*E7 -> 0
B8: Total | C8: =SUM(C4:C7) -> 440 | G8: =SUM(G4:G7) -> 0

Sheet FMV Lease - Pune SEZ
A1: Fair Market Value Lease
B2: 3yrs
A3: Business NB Performance T14 G5, R7P-8840U (3.3GHz,16MB), 14" WUXGA 1920x1200NT, 5MP RGB+IR Cam,SCR,1x32GB, 1x1TB SSD M.2 PCIe G4,AMD Radeon™ 740M,BT5.1 NFA725A (2x2AX),Wired Eth,4cell 52.5Wh, 65W,3yr Premier NBD,TiCRU, KYD,ISE,SBTY,W11P64,Backlit KB:ENG - 21MDS2HM0M | B3: 80000
A4: ThinkPad Essential Wireless Mouse - 4X30M56887 | B4: 1000
A5: Lenovo 15.6’’ Value Plus Backpack - 4X40Y71789 | B5: 900
A6: Base Price of Accessories Excluding GST | B6: =SUM(B4:B5) -> 1900
A7: Quantity | B7: 437
A8: Total Base Price | B8: =B3+B6 -> 81900
A9: No. of payments/Quarters | B9: 12
A10: PTPQ
A11: Quarterly Lease Rent Per Unit (In Advance) | B11: =B10*B8/1000 -> 0
A12: Quarterly lease rent for all units payable in Advance | B12: =B11*B7 -> 0
A13: IRR

Sheet FMV Lease - Pune Non SEZ
A1: Fair Market Value Lease
B2: 3yrs
A3: Business NB Performance T14 G5, R7P-8840U (3.3GHz,16MB), 14" WUXGA 1920x1200NT, 5MP RGB+IR Cam,SCR,1x32GB, 1x1TB SSD M.2 PCIe G4,AMD Radeon™ 740M,BT5.1 NFA725A (2x2AX),Wired Eth,4cell 52.5Wh, 65W,3yr Premier NBD,TiCRU, KYD,ISE,SBTY,W11P64,Backlit KB:ENG - 21MDS2HM0M | B3: 80000
A4: ThinkPad Essential Wireless Mouse - 4X30M56887 | B4: 1000
A5: Lenovo 15.6’’ Value Plus Backpack - 4X40Y71789 | B5: 900
A6: Base Price of Accessories Excluding GST | B6: =SUM(B4:B5) -> 1900
A7: Quantity | B7: 866
A8: Total Base Price | B8: =B3+B6 -> 81900
A9: No. of payments/Quarters | B9: 12
A10: PTPQ
A11: Quarterly Lease Rent Per Unit (In Advance) | B11: =B10*B8/1000 -> 0
A12: Quarterly lease rent for all units payable in Advance | B12: =B11*B7 -> 0
A13: IRR

Sheet FMV Lease - GGN
A1: Fair Market Value Lease
B2: 3yrs
A3: Business NB Performance T14 G5, R7P-8840U (3.3GHz,16MB), 14" WUXGA 1920x1200NT, 5MP RGB+IR Cam,SCR,1x32GB, 1x1TB SSD M.2 PCIe G4,AMD Radeon™ 740M,BT5.1 NFA725A (2x2AX),Wired Eth,4cell 52.5Wh, 65W,3yr Premier NBD,TiCRU, KYD,ISE,SBTY,W11P64,Backlit KB:ENG - 21MDS2HM0M | B3: 80000
A4: ThinkPad Essential Wireless Mouse - 4X30M56887 | B4: 1000
A5: Lenovo 15.6’’ Value Plus Backpack - 4X40Y71789 | B5: 900
A6: Base Price of Accessories Excluding GST | B6: =SUM(B4:B5) -> 1900
A7: Quantity | B7: 360
A8: Total Base Price | B8: =B3+B6 -> 81900
A9: No. of payments/Quarters | B9: 12
A10: PTPQ
A11: Quarterly Lease Rent Per Unit (In Advance) | B11: =B10*B8/1000 -> 0
A12: Quarterly lease rent for all units payable in Advance | B12: =B11*B7 -> 0
A13: IRR

Sheet FMV Lease - BLR
A1: Fair Market Value Lease
B2: 3yrs
A3: Business NB Performance T14 G5, R7P-8840U (3.3GHz,16MB), 14" WUXGA 1920x1200NT, 5MP RGB+IR Cam,SCR,1x32GB, 1x1TB SSD M.2 PCIe G4,AMD Radeon™ 740M,BT5.1 NFA725A (2x2AX),Wired Eth,4cell 52.5Wh, 65W,3yr Premier NBD,TiCRU, KYD,ISE,SBTY,W11P64,Backlit KB:ENG - 21MDS2HM0M | B3: 80000
A4: ThinkPad Essential Wireless Mouse - 4X30M56887 | B4: 1000
A5: Lenovo 15.6’’ Value Plus Backpack - 4X40Y71789 | B5: 900
A6: Base Price of Accessories Excluding GST | B6: =SUM(B4:B5) -> 1900
A7: Quantity | B7: 149
A8: Total Base Price | B8: =B3+B6 -> 81900
A9: No. of payments/Quarters | B9: 12
A10: PTPQ
A11: Quarterly Lease Rent Per Unit (In Advance) | B11: =B10*B8/1000 -> 0
A12: Quarterly lease rent for all units payable in Advance | B12: =B11*B7 -> 0
A13: IRR
